tapi/__init__.py
tapi/adapters.py
tapi/exceptions.py
tapi/serializers.py
tapi/tapi.py
tapi_wrapper-2019.12.10.dist-info/LICENSE
tapi_wrapper-2019.12.10.dist-info/METADATA
tapi_wrapper-2019.12.10.dist-info/WHEEL
tapi_wrapper-2019.12.10.dist-info/top_level.txt
tapi_wrapper-2019.12.10.dist-info/RECORD
