Metadata-Version: 2.1
Name: tapi-wrapper
Version: 2019.12.10
Summary: Обертка для написания библиотек для API
Home-page: https://github.com/pavelmaksimov/tapi-wrapper
Author: Pavel Maksimov
License: MIT
Keywords: tapi,tapioca,wrapper,api
Platform: UNKNOWN
Classifier: Programming Language :: Python :: 3
Classifier: License :: OSI Approved :: MIT License
Requires-Python: >=3.5
Requires-Dist: requests[security] (>=2.6)
Requires-Dist: arrow (<1,>=0.6.0)
